codeepy/Example.py
codeepy/__init__.py
codeepy/codeepy.py
codeepy-0.1.1.dist-info/LICENSE
codeepy-0.1.1.dist-info/METADATA
codeepy-0.1.1.dist-info/WHEEL
codeepy-0.1.1.dist-info/top_level.txt
codeepy-0.1.1.dist-info/RECORD
