Metadata-Version: 2.1
Name: codeepy
Version: 0.1.1
Summary: A library for the Codee Robot
Home-page: https://github.com/mefitzgerald/CodeePy
Author: Marita Fitzgerald
Author-email: maritafitzgerald@gmail.com
License: UNKNOWN
Platform: UNKNOWN
Classifier: Programming Language :: Python :: 3.4
Classifier: License :: OSI Approved :: GNU General Public License v3 (GPLv3)
Classifier: Operating System :: OS Independent
Requires-Dist: pyfirmata
Requires-Dist: pyserial
